wb_api/__init__.py
wb_api/base_api.py
wb_api/client.py
wb_api/common.py
wb_api/content.py
wb_api/exceptions.py
wb_api/statistics.py
wb_api/utils.py
wb_api/enum/__init__.py
wb_api/enum/locale.py
wb_api/schemas/__init__.py
wb_api/schemas/common/__init__.py
wb_api/schemas/common/box.py
wb_api/schemas/common/commission.py
wb_api/schemas/common/pallet.py
wb_api/schemas/common/return.py
wb_api/schemas/content/__init__.py
wb_api/schemas/content/charc.py
wb_api/schemas/content/color.py
wb_api/schemas/content/country.py
wb_api/schemas/content/parent.py
wb_api/schemas/content/subject.py
wb_api/schemas/content/tnved.py
wb_api/schemas/statistics/__init__.py
wb_api/schemas/statistics/income.py
wb_api/schemas/statistics/order.py
wb_api/schemas/statistics/realization_report.py
wb_api/schemas/statistics/sale.py
wb_api/schemas/statistics/stock.py
wb_api_sdk-0.3.1.dist-info/METADATA
wb_api_sdk-0.3.1.dist-info/WHEEL
wb_api_sdk-0.3.1.dist-info/top_level.txt
wb_api_sdk-0.3.1.dist-info/RECORD
