Metadata-Version: 2.4
Name: wb-api-sdk
Version: 0.3.1
Summary: WB API Продавца Python Library
Home-page: https://github.com/artemdorozhkin/wb-api
Author: artemdorozhkin
Author-email: aa.dorozhkin@ya.ru
Keywords: wildberries wb api sdk python
Classifier: Programming Language :: Python :: 3.8
Classifier: License :: OSI Approved :: MIT License
Classifier: Operating System :: OS Independent
Requires-Python: >=3.8
Requires-Dist: pydantic==2.8.2
Requires-Dist: requests==2.32.3
Dynamic: author
Dynamic: author-email
Dynamic: classifier
Dynamic: description
Dynamic: description-content-type
Dynamic: home-page
Dynamic: keywords
Dynamic: requires-dist
Dynamic: requires-python
Dynamic: summary
